sn7402/behaviour.v
//================================================================--
// Design Unit	: sn7402 (behaviour) 
//
// File Name	: behaviour.v
//
// Purpose	: model of TTL SN7402 quad and IC
//
// Author	: Daniel Guenther, Vancouver Island University
//
// Environmant	: Icarus
//-------------------------------------------------------------------
// Revision List	
// Version	Author	Date	Changes
// 1.0	   Daniel Guenther   Nov 10 2016    filled in wire connections
//================================================================--

module sn7402 (P1, P2, P3, P4, P5, P6, P7, P8, P9, P10, P11, P12, P13, P14); 

   output reg P1, P4, P10, P13;
   input P2, P3, P5, P6, P8, P9, P11, P12, P7, P14;

   always @(P2, P3, P7, P14) begin

      if ((P14 == 1'b 1) && (P7 == 1'b 0)) begin
         P1 = ~(P2 | P3);
      end  
   end

   always @(P5, P6, P7, P14) begin

      if ((P14 == 1'b 1) && (P7 == 1'b 0)) begin
         P4 = ~(P5 | P6);
      end  
   end

   always @(P8, P9, P7, P14) begin

      if ((P14 == 1'b 1) && (P7 == 1'b 0)) begin
         P10 = ~(P8 | P9);
      end  
   end

   always @(P11, P12, P7, P14) begin

      if ((P14 == 1'b 1) && (P7 == 1'b 0)) begin
         P13 = ~(P11 | P12);
      end  
   end

endmodule

sn7402/tb.v
//================================================================--
// Design Unit  : cew testbench for sn7402
//
// File Name    : tb.cew
//
// Purpose      : design verification
//
// Note         :
//
// Limitations  :
//
// Errors       : none known
//
// Library      : sn7402
//
// Dependences  : none
//
// Author       : Daniel Guenther, Vancouver Island University
//
// System       : icarus (Linux)
//
//------------------------------------------------------------------
// Revision List
// Version     Author            Date           Changes
// 1.0	      Daniel Guenther   Nov 10 2016    new version
//================================================================--












module test_bench();

   integer cew_Test_Count=0;
          integer cew_Error_Count=0;

   wire t_P1, t_P4, t_P10, t_P13;
   reg t_P2, t_P3, t_P5, t_P6, t_P8, t_P9, t_P11, t_P12, t_P7, t_P14;

   sn7402 cut(t_P1, t_P2, t_P3, t_P4, t_P5, t_P6, t_P7, t_P8, t_P9, t_P10, t_P11, t_P12, t_P13, t_P14);

   initial begin
      $dumpfile("test_bench.vcd");
      $dumpvars(0,test_bench);

      t_P14=1; t_P7=0;

      // note, gates are tested sequentially

      cew_Test_Count=cew_Test_Count+1;
          t_P2=0;t_P3=0;#1;
          if ((t_P1) !== (1)) begin
             cew_Error_Count=cew_Error_Count+1;
             $display("\nTest Case ERROR (Ncase) in script at line number 47");
             $display("Actual Value is ", t_P1 );
             $display("Expected Value is ", 1 );
          end

      cew_Test_Count=cew_Test_Count+1;
          t_P2=0;t_P3=1;#1;
          if ((t_P1) !== (0)) begin
             cew_Error_Count=cew_Error_Count+1;
             $display("\nTest Case ERROR (Ncase) in script at line number 48");
             $display("Actual Value is ", t_P1 );
             $display("Expected Value is ", 0 );
          end

      cew_Test_Count=cew_Test_Count+1;
          t_P2=1;t_P3=0;#1;
          if ((t_P1) !== (0)) begin
             cew_Error_Count=cew_Error_Count+1;
             $display("\nTest Case ERROR (Ncase) in script at line number 49");
             $display("Actual Value is ", t_P1 );
             $display("Expected Value is ", 0 );
          end

      cew_Test_Count=cew_Test_Count+1;
          t_P2=1;t_P3=1;#1;
          if ((t_P1) !== (0)) begin
             cew_Error_Count=cew_Error_Count+1;
             $display("\nTest Case ERROR (Ncase) in script at line number 50");
             $display("Actual Value is ", t_P1 );
             $display("Expected Value is ", 0 );
          end


      cew_Test_Count=cew_Test_Count+1;
          t_P5=0;t_P6=0;#1;
          if ((t_P4) !== (1)) begin
             cew_Error_Count=cew_Error_Count+1;
             $display("\nTest Case ERROR (Ncase) in script at line number 52");
             $display("Actual Value is ", t_P4 );
             $display("Expected Value is ", 1 );
          end

      cew_Test_Count=cew_Test_Count+1;
          t_P5=0;t_P6=1;#1;
          if ((t_P4) !== (0)) begin
             cew_Error_Count=cew_Error_Count+1;
             $display("\nTest Case ERROR (Ncase) in script at line number 53");
             $display("Actual Value is ", t_P4 );
             $display("Expected Value is ", 0 );
          end

      cew_Test_Count=cew_Test_Count+1;
          t_P5=1;t_P6=0;#1;
          if ((t_P4) !== (0)) begin
             cew_Error_Count=cew_Error_Count+1;
             $display("\nTest Case ERROR (Ncase) in script at line number 54");
             $display("Actual Value is ", t_P4 );
             $display("Expected Value is ", 0 );
          end

      cew_Test_Count=cew_Test_Count+1;
          t_P5=1;t_P6=1;#1;
          if ((t_P4) !== (0)) begin
             cew_Error_Count=cew_Error_Count+1;
             $display("\nTest Case ERROR (Ncase) in script at line number 55");
             $display("Actual Value is ", t_P4 );
             $display("Expected Value is ", 0 );
          end


      cew_Test_Count=cew_Test_Count+1;
          t_P8=0;t_P9=0;#1;
          if ((t_P10) !== (1)) begin
             cew_Error_Count=cew_Error_Count+1;
             $display("\nTest Case ERROR (Ncase) in script at line number 57");
             $display("Actual Value is ", t_P10 );
             $display("Expected Value is ", 1 );
          end

      cew_Test_Count=cew_Test_Count+1;
          t_P8=0;t_P9=1;#1;
          if ((t_P10) !== (0)) begin
             cew_Error_Count=cew_Error_Count+1;
             $display("\nTest Case ERROR (Ncase) in script at line number 58");
             $display("Actual Value is ", t_P10 );
             $display("Expected Value is ", 0 );
          end

      cew_Test_Count=cew_Test_Count+1;
          t_P8=1;t_P9=0;#1;
          if ((t_P10) !== (0)) begin
             cew_Error_Count=cew_Error_Count+1;
             $display("\nTest Case ERROR (Ncase) in script at line number 59");
             $display("Actual Value is ", t_P10 );
             $display("Expected Value is ", 0 );
          end

      cew_Test_Count=cew_Test_Count+1;
          t_P8=1;t_P9=1;#1;
          if ((t_P10) !== (0)) begin
             cew_Error_Count=cew_Error_Count+1;
             $display("\nTest Case ERROR (Ncase) in script at line number 60");
             $display("Actual Value is ", t_P10 );
             $display("Expected Value is ", 0 );
          end


      cew_Test_Count=cew_Test_Count+1;
          t_P11=0;t_P12=0;#1;
          if ((t_P13) !== (1)) begin
             cew_Error_Count=cew_Error_Count+1;
             $display("\nTest Case ERROR (Ncase) in script at line number 62");
             $display("Actual Value is ", t_P13 );
             $display("Expected Value is ", 1 );
          end

      cew_Test_Count=cew_Test_Count+1;
          t_P11=0;t_P12=1;#1;
          if ((t_P13) !== (0)) begin
             cew_Error_Count=cew_Error_Count+1;
             $display("\nTest Case ERROR (Ncase) in script at line number 63");
             $display("Actual Value is ", t_P13 );
             $display("Expected Value is ", 0 );
          end

      cew_Test_Count=cew_Test_Count+1;
          t_P11=1;t_P12=0;#1;
          if ((t_P13) !== (0)) begin
             cew_Error_Count=cew_Error_Count+1;
             $display("\nTest Case ERROR (Ncase) in script at line number 64");
             $display("Actual Value is ", t_P13 );
             $display("Expected Value is ", 0 );
          end

      cew_Test_Count=cew_Test_Count+1;
          t_P11=1;t_P12=1;#1;
          if ((t_P13) !== (0)) begin
             cew_Error_Count=cew_Error_Count+1;
             $display("\nTest Case ERROR (Ncase) in script at line number 65");
             $display("Actual Value is ", t_P13 );
             $display("Expected Value is ", 0 );
          end


      $display("\n**********Summary**********\n");
          $display("Total number of test cases = %d \n", cew_Test_Count);
          $display("Total number of test cases in error = %d \n", cew_Error_Count);

      #1 $finish();
   end

endmodule

sn7402/test_bench.vcd
$date
	Thu Nov 10 17:43:19 2016
$end
$version
	Icarus Verilog
$end
$timescale
	1s
$end
$scope module test_bench $end
$var wire 1 ! t_P1 $end
$var wire 1 " t_P10 $end
$var wire 1 # t_P13 $end
$var wire 1 $ t_P4 $end
$var integer 32 % cew_Error_Count [31:0] $end
$var integer 32 & cew_Test_Count [31:0] $end
$var reg 1 ' t_P11 $end
$var reg 1 ( t_P12 $end
$var reg 1 ) t_P14 $end
$var reg 1 * t_P2 $end
$var reg 1 + t_P3 $end
$var reg 1 , t_P5 $end
$var reg 1 - t_P6 $end
$var reg 1 . t_P7 $end
$var reg 1 / t_P8 $end
$var reg 1 0 t_P9 $end
$scope module cut $end
$var wire 1 1 P11 $end
$var wire 1 2 P12 $end
$var wire 1 3 P14 $end
$var wire 1 4 P2 $end
$var wire 1 5 P3 $end
$var wire 1 6 P5 $end
$var wire 1 7 P6 $end
$var wire 1 8 P7 $end
$var wire 1 9 P8 $end
$var wire 1 : P9 $end
$var reg 1 ; P1 $end
$var reg 1 < P10 $end
$var reg 1 = P13 $end
$var reg 1 > P4 $end
$upscope $end
$upscope $end
$enddefinitions $end
#0
$dumpvars
x>
x=
x<
1;
x:
x9
08
x7
x6
05
04
13
x2
x1
x0
x/
0.
x-
x,
0+
0*
1)
x(
x'
b1 &
b0 %
x$
x#
x"
1!
$end
#1
0;
0!
1+
15
b10 &
#2
0+
05
1*
14
b11 &
#3
1+
15
b100 &
#4
1>
1$
0-
07
0,
06
b101 &
#5
0>
0$
1-
17
b110 &
#6
0-
07
1,
16
b111 &
#7
1-
17
b1000 &
#8
1<
1"
00
0:
0/
09
b1001 &
#9
0<
0"
10
1:
b1010 &
#10
00
0:
1/
19
b1011 &
#11
10
1:
b1100 &
#12
1=
1#
0(
02
0'
01
b1101 &
#13
0=
0#
1(
12
b1110 &
#14
0(
02
1'
11
b1111 &
#15
1(
12
b10000 &
